{
  "id": "B93",
  "agent_details": {
    "code": "#0003C",
    "native_language": "Nepali",
    "gender": "Male",
    "age": 32,
    "city": "Gangtok",
    "country": "India"
  },
  "respondent_details": {
    "first_name": "Kennedy",
    "gender": "Male",
    "age": 20,
    "country": "Kenya",
    "language_native": "Swahili",
    "languages_known": ["English", "swahili", "kamba", "kikuyu"],
    "accent_or_dialect": "Swahili English accent",
    "call_language": "English"
  },
  "consent": "Yes",
  "recording_details": {
    "recording_link_agent": [
      "https://drive.google.com/file/d/14ZBrjH563QcYGCNDIwpPItOF7aS33AUP/view?usp=drive_link",
      "https://drive.google.com/file/d/1VlnmNxKflsnA7xoBXsd-5AVliHlWndQW/view?usp=drive_link"
    ],
    "recording_link_respondent": [
      "https://drive.google.com/file/d/174P7tFJwWGhgIrunKJHMpVzuIr6n3x2E/view?usp=drive_link",
      "https://drive.google.com/file/d/1vHTP0b5CJ7YUGYveCCy8-FapyJ-EGVU_/view?usp=drive_link"
    ],
    "duration": "33.32 min",
    "file_size_agent": "177.39 MB",
    "file_size_respondent": "171.17 MB",
    "device_used": "Infinix smart 7(phone)",
    "noise_level": "Low",
    "notes": "Ok (low voice)"
  }
}
