{
  "id": "P72",
  "agent_details": {
    "code": "#0001C",
    "native_language": "Nepali",
    "gender": "Male",
    "age": 36,
    "city": "Kathmandu",
    "country": "Nepal"
  },
  "respondent_details": {
    "first_name": "Msanifu",
    "gender": "Male",
    "age": 23,
    "country": "Kenya",
    "language_native": "Mijikenda",
    "languages_known": ["English", "Swahili", "Mijikenda"],
    "accent_or_dialect": "Kenyan Accent",
    "call_language": "English"
  },
  "consent": "Yes",
  "recording_details": {
    "recording_link_agent": [
      "https://drive.google.com/file/d/1Aqoqj4_ntLlTj_5HQkIR3KwSCDz7cLs9/view?usp=drive_link"
    ],
    "recording_link_respondent": [
      "https://drive.google.com/file/d/1KKR0TqogOlXcdorY9xIVm_2UV4ayIuv7/view?usp=drive_link"
    ],
    "duration": "31:27 min",
    "file_size_agent": "158.7 MB",
    "file_size_respondent": "158.8 MB",
    "device_used": "Samsung 16",
    "noise_level": "Low",
    "notes": "ok(but very low voice)"
  }
}
