{
  "id": "ST24",
  "agent_details": {
    "code": "#0005C",
    "native_language": "Nepali",
    "gender": "Female",
    "age": 26,
    "city": "Kathmandu",
    "country": "Nepal"
  },
  "respondent_details": {
    "first_name": "Cynthia",
    "gender": "Female",
    "age": 23,
    "country": "Kenya",
    "language_native": "Swahili",
    "languages_known": [
      "English", "Swahili", "Kamba"
    ],
    "accent_or_dialect": "American",
    "call_language": "English"
  },
  "consent": "Yes",
  "recording_details": {
    "recording_link_agent": [
      "https://drive.google.com/file/d/1yfTWMO07jnJmP7S1zdU-h-KlnUzZsDWW/view"
    ],
    "recording_link_respondent": [
      "https://drive.google.com/file/d/1sinNBwLwA9iXupMpc8UA-KnkvFIfrLBi/view"
    ],
    "duration": "38:15 min",
    "file_size_agent": "193 MB",
    "file_size_respondent": "193 MB",
    "device_used": "Samsung A05",
    "noise_level": "Low",
    "notes": "Ok audio is good"
  }
}